spoox/__init__.py
spoox/spoox_cli.py
spoox/spoox_headless.py
spoox/utils.py
spoox/utils_cli.py
spoox/agents/__init__.py
spoox/agents/agent_system.py
spoox/agents/errors.py
spoox/agents/prompts.py
spoox/agents/mas/__init__.py
spoox/agents/mas/agent_system_spoox_large.py
spoox/agents/mas/agent_system_spoox_medium.py
spoox/agents/mas/agent_system_spoox_small.py
spoox/agents/mas/base_agent.py
spoox/agents/mas/messages.py
spoox/agents/mas/agents/__init__.py
spoox/agents/mas/agents/approver_agent.py
spoox/agents/mas/agents/explorer_agent.py
spoox/agents/mas/agents/prompts.py
spoox/agents/mas/agents/refiner_agent.py
spoox/agents/mas/agents/solver_agent.py
spoox/agents/mas/agents/subtaskplanner_agent.py
spoox/agents/mas/agents/subtasksolver_agent.py
spoox/agents/mas/agents/summarizer_agent.py
spoox/agents/mas/agents/tester_agent.py
spoox/agents/singleton/__init__.py
spoox/agents/singleton/agent_system_singleton.py
spoox/agents/singleton/messages.py
spoox/agents/singleton/prompts.py
spoox/agents/singleton/singelton_agent.py
spoox/environment/__init__.py
spoox/environment/environment.py
spoox/environment/local_environment.py
spoox/environment/code_executors/__init__.py
spoox/environment/code_executors/code_executor_local.py
spoox/environment/code_executors/tmux_terminal_session.py
spoox/environment/tools/__init__.py
spoox/environment/tools/python_tool.py
spoox/environment/tools/shell_tool.py
spoox/environment/tools/terminal_tool.py
spoox/environment/tools/utils.py
spoox/interface/__init__.py
spoox/interface/cli_interface.py
spoox/interface/interface.py
spoox/interface/log_interface.py
spoox-0.3.1.dist-info/METADATA
spoox-0.3.1.dist-info/WHEEL
spoox-0.3.1.dist-info/entry_points.txt
spoox-0.3.1.dist-info/licenses/LICENSE
spoox-0.3.1.dist-info/RECORD
