Metadata-Version: 2.4
Name: spoox
Version: 0.3.1
Summary: SPOOX – SPlit lOOp eXpand – Terminal Assistant
Project-URL: Homepage, https://github.com/plaume8/spoox
Project-URL: Issues, https://github.com/plaume8/spoox/issues
Author-email: Linus Sander <linus.sander@tum.de>, Fengjunjie Pan <f.pan@tum.de>
License-Expression: Apache-2.0
License-File: LICENSE
Classifier: Operating System :: OS Independent
Classifier: Programming Language :: Python :: 3
Requires-Python: >=3.10
Requires-Dist: anthropic>=0.73.0
Requires-Dist: art>=6
Requires-Dist: autogen-core==0.7.5
Requires-Dist: autogen-ext==0.7.5
Requires-Dist: ddgs>=9
Requires-Dist: docker-py>=1.10.6
Requires-Dist: langchain-community>=0.4.1
Requires-Dist: nest-asyncio>=1.6.0
Requires-Dist: ollama>=0.6.1
Requires-Dist: openai>=1.99
Requires-Dist: proxytypes>=0.10.0
Requires-Dist: pydantic>=2.12.4
Requires-Dist: python-dotenv>=1.2.1
Requires-Dist: questionary>=2.1.1
Requires-Dist: rich>=14.2.0
Requires-Dist: tiktoken>=0.9
Requires-Dist: typing-extensions>=4.15.0
Requires-Dist: yaspin>=3
